doit_graph
