Metadata-Version: 1.1
Name: doit-graph
Version: 0.1.1
Summary: doit cmd plugin: create task's dependency-graph image
Home-page: http://github.com/pydoit/doit-graph
Author: Eduardo Naufel Schettino
Author-email: UNKNOWN
License: MIT
Keywords: doit graph graphviz
Platform: UNKNOWN
Classifier: Development Status :: 5 - Production/Stable
Classifier: Environment :: Console
Classifier: License :: OSI Approved :: MIT License
Classifier: Natural Language :: English
Classifier: Operating System :: OS Independent
Classifier: Operating System :: POSIX
Classifier: Programming Language :: Python :: 3
Classifier: Programming Language :: Python :: 3.5
Classifier: Programming Language :: Python :: 3.6
Classifier: Programming Language :: Python :: 3.7
Classifier: Intended Audience :: Developers
